README.md
setup.py
dweessenger/__init__.py
dweessenger.egg-info/PKG-INFO
dweessenger.egg-info/SOURCES.txt
dweessenger.egg-info/dependency_links.txt
dweessenger.egg-info/requires.txt
dweessenger.egg-info/top_level.txt