Metadata-Version: 2.1
Name: dweessenger
Version: 0.1.1
Summary: A simple python package for messaging through free dweet service.
Home-page: https://github.com/jacklinquan/dweessenger
Author: Quan Lin
Author-email: jacklinquan@gmail.com
License: MIT
Platform: UNKNOWN
Classifier: Development Status :: 3 - Alpha
Classifier: License :: OSI Approved :: MIT License
Classifier: Programming Language :: Python :: 2
Classifier: Programming Language :: Python :: 2.7
Classifier: Programming Language :: Python :: 3
